{
  "date": "2026-01-13",
  "totalBrands": 23,
  "totalProducts": 474,
  "uniqueSlugs": 474,
  "duplicateSlugs": 0,
  "brands": [
    {
      "brandSlug": "42birds",
      "productCount": 10
    },
    {
      "brandSlug": "aloyoga",
      "productCount": 4
    },
    {
      "brandSlug": "ananday",
      "productCount": 4
    },
    {
      "brandSlug": "bala",
      "productCount": 20
    },
    {
      "brandSlug": "gaiam",
      "productCount": 35
    },
    {
      "brandSlug": "gayo",
      "productCount": 4
    },
    {
      "brandSlug": "heathyoga",
      "productCount": 6
    },
    {
      "brandSlug": "houseofmats",
      "productCount": 21
    },
    {
      "brandSlug": "jadeyoga",
      "productCount": 14
    },
    {
      "brandSlug": "keep",
      "productCount": 7
    },
    {
      "brandSlug": "liforme",
      "productCount": 41
    },
    {
      "brandSlug": "manduka",
      "productCount": 16
    },
    {
      "brandSlug": "okoliving",
      "productCount": 18
    },
    {
      "brandSlug": "scoria",
      "productCount": 44
    },
    {
      "brandSlug": "sensu",
      "productCount": 3
    },
    {
      "brandSlug": "shaktiwarrior",
      "productCount": 32
    },
    {
      "brandSlug": "stakt",
      "productCount": 3
    },
    {
      "brandSlug": "thesatoriconcept",
      "productCount": 12
    },
    {
      "brandSlug": "woloyoga",
      "productCount": 8
    },
    {
      "brandSlug": "yogadesignlab",
      "productCount": 49
    },
    {
      "brandSlug": "yogamatters",
      "productCount": 53
    },
    {
      "brandSlug": "yogibare",
      "productCount": 10
    },
    {
      "brandSlug": "yolohayoga",
      "productCount": 60
    }
  ],
  "priceStats": {
    "min": 19.98,
    "max": 1138,
    "average": 137.87369198312228,
    "median": 110
  },
  "materialBreakdown": {
    "Cork": 143,
    "PVC": 39,
    "Natural Rubber": 159,
    "Cotton": 23,
    "TPE": 13,
    "Jute": 3,
    "NBR": 2
  },
  "featureBreakdown": {
    "Eco-Friendly": 356,
    "Non-Slip": 372,
    "Lightweight": 172,
    "Extra Wide": 221,
    "Antimicrobial": 106,
    "Extra Thick": 161,
    "Extra Long": 81,
    "Reversible": 19,
    "Premium": 91,
    "Alignment Marks": 134,
    "Closed-Cell": 26
  }
}